rankingmetrics/__init__.py
rankingmetrics/errs.py
rankingmetrics/ndcgs.py
ranking_metrics-0.1.1.dist-info/METADATA
ranking_metrics-0.1.1.dist-info/WHEEL
ranking_metrics-0.1.1.dist-info/top_level.txt
ranking_metrics-0.1.1.dist-info/RECORD
